jbossta.py
setup.py
jbossta.egg-info/PKG-INFO
jbossta.egg-info/SOURCES.txt
jbossta.egg-info/dependency_links.txt
jbossta.egg-info/entry_points.txt
jbossta.egg-info/requires.txt
jbossta.egg-info/top_level.txt