Metadata-Version: 1.1
Name: jbossta
Version: 0.0.1
Summary: This is a script that provides a "save and run" for JSPs in a JBoss application like PHP does
Home-page: https://github.com/luisffc/jbossta
Author: Luis FF Cavalcante
Author-email: luis@coffeetech.com.br
License: UNKNOWN
Platform: UNKNOWN
Classifier: Development Status :: 3 - Alpha
Classifier: Environment :: Console
Classifier: Environment :: Web Environment
Classifier: License :: OSI Approved :: GNU General Public License (GPL)
Classifier: Natural Language :: English
Classifier: Programming Language :: Python :: 2
Classifier: Topic :: Software Development :: Build Tools
Classifier: Topic :: Utilities
Classifier: Operating System :: OS Independent
